MANIFEST.in
README.txt
setup.py
lfs_theme/__init__.py
lfs_theme.egg-info/PKG-INFO
lfs_theme.egg-info/SOURCES.txt
lfs_theme.egg-info/dependency_links.txt
lfs_theme.egg-info/not-zip-safe
lfs_theme.egg-info/requires.txt
lfs_theme.egg-info/top_level.txt
lfs_theme/locale/cs/LC_MESSAGES/django.mo
lfs_theme/locale/cs/LC_MESSAGES/django.po
lfs_theme/locale/de/LC_MESSAGES/django.mo
lfs_theme/locale/de/LC_MESSAGES/django.po
lfs_theme/locale/en/LC_MESSAGES/django.po
lfs_theme/locale/es/LC_MESSAGES/django.mo
lfs_theme/locale/es/LC_MESSAGES/django.po
lfs_theme/locale/es_MX/LC_MESSAGES/django.mo
lfs_theme/locale/es_MX/LC_MESSAGES/django.po
lfs_theme/locale/fr/LC_MESSAGES/django.mo
lfs_theme/locale/fr/LC_MESSAGES/django.po
lfs_theme/locale/it/LC_MESSAGES/django.mo
lfs_theme/locale/it/LC_MESSAGES/django.po
lfs_theme/locale/nl/LC_MESSAGES/django.mo
lfs_theme/locale/nl/LC_MESSAGES/django.po
lfs_theme/locale/pl/LC_MESSAGES/django.mo
lfs_theme/locale/pl/LC_MESSAGES/django.po
lfs_theme/locale/ro/LC_MESSAGES/django.mo
lfs_theme/locale/ro/LC_MESSAGES/django.po
lfs_theme/locale/ru/LC_MESSAGES/django.mo
lfs_theme/locale/ru/LC_MESSAGES/django.po
lfs_theme/locale/zh_CN/LC_MESSAGES/django.mo
lfs_theme/locale/zh_CN/LC_MESSAGES/django.po
lfs_theme/locale/zh_TW/LC_MESSAGES/django.mo
lfs_theme/locale/zh_TW/LC_MESSAGES/django.po
lfs_theme/static/.DS_Store
lfs_theme/static/blueprint/ie.css
lfs_theme/static/blueprint/print.css
lfs_theme/static/blueprint/screen.css
lfs_theme/static/blueprint/plugins/buttons/readme.txt
lfs_theme/static/blueprint/plugins/buttons/screen.css
lfs_theme/static/blueprint/plugins/buttons/icons/cross.png
lfs_theme/static/blueprint/plugins/buttons/icons/key.png
lfs_theme/static/blueprint/plugins/buttons/icons/tick.png
lfs_theme/static/blueprint/plugins/fancy-type/readme.txt
lfs_theme/static/blueprint/plugins/fancy-type/screen.css
lfs_theme/static/blueprint/plugins/link-icons/readme.txt
lfs_theme/static/blueprint/plugins/link-icons/screen.css
lfs_theme/static/blueprint/plugins/link-icons/icons/doc.png
lfs_theme/static/blueprint/plugins/link-icons/icons/email.png
lfs_theme/static/blueprint/plugins/link-icons/icons/external.png
